computerSitTimer/CountDowner.py
computerSitTimer/GraphicalUI.py
computerSitTimer/MultiprocessingWithException.py
computerSitTimer/__init__.py
computerSitTimer/__main__.py
computerSitTimer/tmp_multiprocessing.py
computerSitTimer/media/MediaHelper.py
computerSitTimer/media/__init__.py
computerSitTimer/media/icon-play.png
computerSitTimer/media/icon-stop.png
tests/TestHelper.py
tests/__init__.py
tests/test_countDowner.py
tests/test_mediaHelper.py
tests/test_ui.py
computerSitTimer-0.1.3.dist-info/LICENSE
computerSitTimer-0.1.3.dist-info/METADATA
computerSitTimer-0.1.3.dist-info/WHEEL
computerSitTimer-0.1.3.dist-info/entry_points.txt
computerSitTimer-0.1.3.dist-info/top_level.txt
computerSitTimer-0.1.3.dist-info/RECORD
