Metadata-Version: 2.1
Name: computerSitTimer
Version: 0.1.3
Summary: A simple timer in tray to prevent sitting too long.
Home-page: https://github.com/tjangoW/computerSitTimer
Author: tjango
License: UNKNOWN
Platform: UNKNOWN
Classifier: Programming Language :: Python :: 3
Classifier: License :: OSI Approved :: MIT License
Classifier: Operating System :: OS Independent
Classifier: Development Status :: 3 - Alpha
Classifier: Intended Audience :: End Users/Desktop
Classifier: Natural Language :: English
Classifier: Topic :: Desktop Environment
Requires-Python: ~=3.5
License-File: LICENSE
Requires-Dist: pySimpleGUIQt
